pytransmission/__init__.py
pytransmission/py.typed
pytransmission/transmission.py
pytransmission-0.0.8.dist-info/METADATA
pytransmission-0.0.8.dist-info/WHEEL
pytransmission-0.0.8.dist-info/top_level.txt
pytransmission-0.0.8.dist-info/RECORD
